Metadata-Version: 1.0
Name: envtransformer
Version: 0.1
Summary: Environment Variable Swapper
Home-page: https://github.com/nimboya/envtransformer
Author: Ewere Diagboya
Author-email: nimboya@gmail.com
License: Apache License 2.0
Platform: UNKNOWN
